<?xml version="1.0" encoding="UTF-8"?>
<MetaDataObject xmlns="http://v8.1c.ru/8.3/MDClasses" xmlns:app="http://v8.1c.ru/8.2/managed-application/core" xmlns:cfg="http://v8.1c.ru/8.1/data/enterprise/current-config" xmlns:cmi="http://v8.1c.ru/8.2/managed-application/cmi" xmlns:ent="http://v8.1c.ru/8.1/data/enterprise" xmlns:lf="http://v8.1c.ru/8.2/managed-application/logform" xmlns:style="http://v8.1c.ru/8.1/data/ui/style" xmlns:sys="http://v8.1c.ru/8.1/data/ui/fonts/system" xmlns:v8="http://v8.1c.ru/8.1/data/core" xmlns:v8ui="http://v8.1c.ru/8.1/data/ui" xmlns:web="http://v8.1c.ru/8.1/data/ui/colors/web" xmlns:win="http://v8.1c.ru/8.1/data/ui/colors/windows" xmlns:xen="http://v8.1c.ru/8.3/xcf/enums" xmlns:xpr="http://v8.1c.ru/8.3/xcf/predef" xmlns:xr="http://v8.1c.ru/8.3/xcf/readable" xmlns:xs="http://www.w3.org/2001/XMLSchema" xmlns:xsi="http://www.w3.org/2001/XMLSchema-instance" version="2.20">
	<CommonCommand uuid="41f87891-ddd5-4e0f-a4f2-8039fb71981b">
		<Properties>
			<Name>СтруктураПодчиненности</Name>
			<Synonym>
				<v8:item>
					<v8:lang>ru</v8:lang>
					<v8:content>Связанные документы</v8:content>
				</v8:item>
			</Synonym>
			<Comment/>
			<Group>FormCommandBarImportant</Group>
			<Representation>Auto</Representation>
			<ToolTip/>
			<Picture>
				<xr:Ref>CommonPicture.СтруктураПодчиненностиДокумента</xr:Ref>
				<xr:LoadTransparent>true</xr:LoadTransparent>
			</Picture>
			<Shortcut/>
			<IncludeHelpInContents>false</IncludeHelpInContents>
			<CommandParameterType>
				<v8:Type>cfg:DocumentRef.упИсходящаяПретензия</v8:Type>
				<v8:Type>cfg:DocumentRef.упПодтверждениеЗаявкиНаТС</v8:Type>
				<v8:Type>cfg:DocumentRef.упШтраф</v8:Type>
				<v8:Type>cfg:DocumentRef.упПередачаТранспортногоСредстваПодразделению</v8:Type>
				<v8:Type>cfg:DocumentRef.упСписаниеПлановПоЗаданиюНаПеревозку</v8:Type>
				<v8:Type>cfg:DocumentRef.упЗапросУсловийПеревозки</v8:Type>
				<v8:Type>cfg:DocumentRef.упКорректировкаРейса</v8:Type>
				<v8:Type>cfg:DocumentRef.упИзменениеПараметровГрузовыхМест</v8:Type>
				<v8:Type>cfg:DocumentRef.упСнятиеСУчетаТранспортногоСредства</v8:Type>
				<v8:Type>cfg:DocumentRef.упЗаявкаНаРемонтИТОТС</v8:Type>
				<v8:Type>cfg:DocumentRef.упРегистрацияЗадолженностиПоДокументамРейса</v8:Type>
				<v8:Type>cfg:DocumentRef.упВходящаяПретензия</v8:Type>
				<v8:Type>cfg:DocumentRef.упИзменениеСостоянияТранспортногоСредства</v8:Type>
				<v8:Type>cfg:DocumentRef.упСлужебноеРасследование</v8:Type>
				<v8:Type>cfg:DocumentRef.упСобытиеМониторинга</v8:Type>
				<v8:Type>cfg:DocumentRef.упАвансовыйОтчет</v8:Type>
				<v8:Type>cfg:DocumentRef.упРейс</v8:Type>
				<v8:Type>cfg:DocumentRef.упСчетНаОплатуЗаказчику</v8:Type>
				<v8:Type>cfg:DocumentRef.упФактическиеДоходы</v8:Type>
				<v8:Type>cfg:DocumentRef.упОтчетИнкассатора</v8:Type>
				<v8:Type>cfg:DocumentRef.упПрохождениеТочки</v8:Type>
				<v8:Type>cfg:DocumentRef.упПринятиеКУчетуТранспортногоСредства</v8:Type>
				<v8:Type>cfg:DocumentRef.упПрисоединениеОтсоединениеПрицепа</v8:Type>
				<v8:Type>cfg:DocumentRef.упЗаявкаНаПеревозкуГруза</v8:Type>
				<v8:Type>cfg:DocumentRef.упЗаданиеНаПеревозкуГруза</v8:Type>
				<v8:Type>cfg:DocumentRef.упФактическиеРасходы</v8:Type>
				<v8:Type>cfg:DocumentRef.упЗаявкаНаТС</v8:Type>
				<v8:Type>cfg:DocumentRef.упДоверенность</v8:Type>
				<v8:Type>cfg:DocumentRef.упРегистрацияОтложенныхРаботПоРейсу</v8:Type>
				<v8:Type>cfg:DocumentRef.упРемонтИТОТС</v8:Type>
				<v8:Type>cfg:DocumentRef.упПутевойЛист</v8:Type>
				<v8:Type>cfg:DocumentRef.упПроисшествиеВПути</v8:Type>
				<v8:Type>cfg:DocumentRef.упПредложениеПеревозчика</v8:Type>
			</CommandParameterType>
			<ParameterUseMode>Single</ParameterUseMode>
			<ModifiesData>false</ModifiesData>
			<OnMainServerUnavalableBehavior>Auto</OnMainServerUnavalableBehavior>
		</Properties>
	</CommonCommand>
</MetaDataObject>